Utube/__init__.py
Utube/functions/__init__.py
Utube/functions/function01.py
Utube/scripts/__init__.py
Utube/scripts/en.py
Utube/scripts/eo.py
utube_dl-0.0.1.dist-info/LICENSE
utube_dl-0.0.1.dist-info/METADATA
utube_dl-0.0.1.dist-info/WHEEL
utube_dl-0.0.1.dist-info/top_level.txt
utube_dl-0.0.1.dist-info/RECORD
