Metadata-Version: 2.1
Name: utube-dl
Version: 0.0.1
Summary: ㅤ
Home-page: https://github.com/Monisha
License: MIT
Keywords: python,youtube,monisha
Classifier: Natural Language :: English
Classifier: Intended Audience :: Developers
Classifier: Operating System :: OS Independent
Classifier: Programming Language :: Python :: 3.10
Classifier: Programming Language :: Python :: 3.11
Classifier: Programming Language :: Python :: 3.12
Classifier: Topic :: Software Development :: Libraries
Classifier: Topic :: Software Development :: Libraries :: Python Modules
Classifier: License :: OSI Approved :: GNU Lesser General Public License v3 (LGPLv3)
Requires-Python: ~=3.10
License-File: LICENSE
